finalsa/s3/client/__init__.py
finalsa/s3/client/client/__init__.py
finalsa/s3/client/client/client.py
finalsa/s3/client/interface/__init__.py
finalsa/s3/client/interface/client.py
finalsa/s3/client/tests/__init__.py
finalsa/s3/client/tests/client.py
finalsa/s3/client/tests/models/__init__.py
finalsa/s3/client/tests/models/document.py
finalsa_s3_client-0.1.6.dist-info/METADATA
finalsa_s3_client-0.1.6.dist-info/WHEEL
finalsa_s3_client-0.1.6.dist-info/licenses/LICENSE.md
finalsa_s3_client-0.1.6.dist-info/RECORD
