Metadata-Version: 2.4
Name: finalsa-s3-client
Version: 0.1.6
Summary: A simple client to interact with s3
Project-URL: Homepage, https://github.com/finvalsa/finalsa-s3-client
Author-email: Luis Jimenez <luis@finalsa.com>
License: MIT License
License-File: LICENSE.md
Keywords: aws,client,finalsa,s3
Requires-Python: >=3.10
Requires-Dist: boto3>=1.36.7
